elan_data/__init__.py
elan_data/elan_utils.py
elan_data/py.typed
elan_data-1.7.3.dist-info/METADATA
elan_data-1.7.3.dist-info/WHEEL
elan_data-1.7.3.dist-info/top_level.txt
elan_data-1.7.3.dist-info/RECORD
